MANIFEST.in
README.md
build.py
pyproject.toml
deepsurfer/__init__.py
deepsurfer/config.py
deepsurfer/device.py
deepsurfer/io.py
deepsurfer/label.py
deepsurfer/nearest.py
deepsurfer/normalize.py
deepsurfer/optional.py
deepsurfer/preprocess.py
deepsurfer/training.py
deepsurfer.egg-info/PKG-INFO
deepsurfer.egg-info/SOURCES.txt
deepsurfer.egg-info/dependency_links.txt
deepsurfer.egg-info/entry_points.txt
deepsurfer.egg-info/requires.txt
deepsurfer.egg-info/top_level.txt
deepsurfer/extension/__init__.py
deepsurfer/extension/extension.cxx
deepsurfer/extension/extension.py
deepsurfer/extension/intersection.cu
deepsurfer/extension/nearest.cu
deepsurfer/image/__init__.py
deepsurfer/image/unet.py
deepsurfer/modules/__init__.py
deepsurfer/modules/align.py
deepsurfer/modules/crop.py
deepsurfer/modules/strip.py
deepsurfer/modules/topofit.py
deepsurfer/resource/iotypes/fs.yaml
deepsurfer/resource/iotypes/si.yaml
deepsurfer/resource/models/brain-cropping-1.pt
deepsurfer/resource/models/synthstrip-1.pt
deepsurfer/resource/models/template-alignment-1.pt
deepsurfer/resource/models/topofit-beta-5.pt
deepsurfer/resource/template/cortex-int-lh.srf
deepsurfer/resource/template/cortex-int-rh.srf
deepsurfer/resource/template/folding-atlas.tif
deepsurfer/resource/template/left-to-right.lta
deepsurfer/resource/template/orienting-seg.mgz
deepsurfer/resource/template/sphere-reg.srf
deepsurfer/resource/template/surf-topology.npz
deepsurfer/surf/__init__.py
deepsurfer/surf/conv.py
deepsurfer/surf/deform.py
deepsurfer/surf/mesh.py
deepsurfer/surf/template.py
deepsurfer/system/__init__.py
deepsurfer/system/commandline.py
deepsurfer/system/formatting.py
deepsurfer/system/io.py
deepsurfer/system/parse.py
deepsurfer/system/utility.py
deepsurfer/system/version.py
tests/test_deepsurfer.py